db/__init__.py
db/mysql.py
cstool-0.0.3.dist-info/LICENSE
cstool-0.0.3.dist-info/METADATA
cstool-0.0.3.dist-info/WHEEL
cstool-0.0.3.dist-info/top_level.txt
cstool-0.0.3.dist-info/RECORD
