Metadata-Version: 2.1
Name: cstool
Version: 0.0.3
Summary: cs utils
Home-page: https://github.com/362228416/cstool-py
Author: CS
Author-email: 362228416@qq.com
License: UNKNOWN
Platform: UNKNOWN
Classifier: Programming Language :: Python :: 3
Classifier: License :: OSI Approved :: MIT License
Classifier: Operating System :: OS Independent
Requires-Python: >=3.6
